README.md
setup.py
UTN_Dataset/__init__.py
UTN_Dataset/common_variables.py
UTN_Dataset.egg-info/PKG-INFO
UTN_Dataset.egg-info/SOURCES.txt
UTN_Dataset.egg-info/dependency_links.txt
UTN_Dataset.egg-info/entry_points.txt
UTN_Dataset.egg-info/requires.txt
UTN_Dataset.egg-info/top_level.txt
UTN_Dataset/funciones/__init__.py
UTN_Dataset/funciones/auxiliares.py
UTN_Dataset/funciones/auxiliares.pyi
UTN_Dataset/utn_listas/__init__.py
UTN_Dataset/utn_listas/pokemones.py