Metadata-Version: 2.1
Name: UTN_Dataset
Version: 1.0.5.1
Summary: Set de datos con informacion de pokemones
Home-page: https://pypi.org/project/UTN-Dataset/
Author: Facundo Falcone
Author-email: ffalcone@fra.utn.edu.ar
Maintainer: Facundo Falcone
Maintainer-email: ffalcone@fra.utn.edu.ar
Keywords: UTN_Dataset,UTN-FRA
Classifier: Programming Language :: Python :: 3
Classifier: License :: OSI Approved :: MIT License
Classifier: Operating System :: OS Independent
Requires: setuptools
Requires: tabulate
Requires-Python: >=3.11
Requires-Dist: setuptools
Requires-Dist: tabulate
